mapfeat/__init__.py
mapfeat/cyparser.cp39-win_amd64.pyd
mapfeat-0.1.8.dist-info/METADATA
mapfeat-0.1.8.dist-info/WHEEL
mapfeat-0.1.8.dist-info/top_level.txt
mapfeat-0.1.8.dist-info/RECORD
