Metadata-Version: 2.4
Name: mapfeat
Version: 0.1.8
Summary: Cython parser for coverage metadata
Author-email: Tom <xauen86@gmail.com>
Requires-Python: >=3.8
